[
{
"content_id": "REALIA:4.2.2",
"reference_id": "REALIA:4.2.2",
"version": "1.0.4",
"title": "Tabernacle altar",
"media_type": "Text",
"index_reference": "4.2.2",
"language": "eng",
"review_level": "None",
"content": "<style>\nh1.thlex-title { font-size: 1.3em; margin: 0 0 0.4em; }\n.thlex-key { color: #888; font-size: 0.85em; font-weight: normal; margin-right: 0.4em; }\nnav.thlex-index { margin: 0.5em 0 0.75em; }\nnav.thlex-index ul { margin: 0; padding-left: 1.2em; }\nnav.thlex-index li { margin: 0.15em 0; font-size: 0.95em; }\n.thlex-section { margin: 0.6em 0; }\nh2.thlex-heading { font-size: 1em; margin: 0.5em 0 0.2em; }\nh3.thlex-subheading { font-size: 0.95em; font-weight: normal; font-style: italic; margin: 0.2em 0; }\n.thlex-language-sets { margin: 0.3em 0 0.3em 1em; }\n.thlex-language-set { margin: 0.4em 0; padding-left: 0.75em; border-left: 3px solid #e0e0e0; }\n.thlex-language { font-size: 0.8em; color: #888; margin-right: 0.4em; }\n.thlex-lemma { font-weight: bold; font-family: serif; }\n.thlex-translit { color: #555; font-style: italic; font-size: 0.9em; margin-left: 0.3em; }\n.thlex-refs { font-size: 0.85em; color: #444; margin-top: 0.15em; }\n.thlex-paragraphs p { margin: 0.35em 0; font-size: 0.95em; line-height: 1.5; }\n.thlex-image { margin: 0.5em 0; display: block; }\n.thlex-image img { max-width: 100%; height: auto; display: block; }\nfigcaption.thlex-caption { font-size: 0.85em; color: #555; font-style: italic; margin-top: 0.2em; }\n.thlex-abbr { border-bottom: 1px dotted #888; cursor: help; }\n.thlex-xref { color: #1a5fb4; }\nspan[data-bnType=\"bibleReference\"] { color: #1a5fb4; }\ntable.thlex-table { border-collapse: collapse; font-size: 0.9em; margin: 0.5em 0; }\ntable.thlex-table td { padding: 0.2em 0.6em; vertical-align: top; border: 1px solid #ddd; }\ntable.thlex-table tr:first-child td { font-weight: bold; background: #f5f5f5; }\nul.thlex-index-list { margin: 0.4em 0; padding-left: 1.4em; font-size: 0.95em; line-height: 1.6; }\nul.thlex-index-list ul { margin: 0.1em 0; padding-left: 1.4em; }\n.thlex-index-key { font-weight: bold; font-style: italic; }\n</style><h1 class=\"thlex-title\" id=\"REALIA:4.2.2\"><span class=\"thlex-key\">4.2.2</span> Tabernacle altar</h1><div class=\"thlex-section\">\n<h2 class=\"thlex-heading\">References:</h2>\n<div class=\"thlex-language-sets\">\n<div class=\"thlex-language-set\">\n<span class=\"thlex-language\">Hebrew</span> <span class=\"thlex-lemma\">מִזְבֵּחַ</span> <span class=\"thlex-translit\">(mizbeach)</span>\n<div class=\"thlex-refs\"><a href=\"https://ref.ly/Exod27:1\">EXO 27:1</a>, <a href=\"https://ref.ly/Exod27:1\">EXO 27:1</a>, <a href=\"https://ref.ly/Exod27:5\">EXO 27:5</a>, <a href=\"https://ref.ly/Exod27:5\">EXO 27:5</a>, <a href=\"https://ref.ly/Exod27:6\">EXO 27:6</a>, <a href=\"https://ref.ly/Exod27:7\">EXO 27:7</a>, <a href=\"https://ref.ly/Exod28:43\">EXO 28:43</a>, <a href=\"https://ref.ly/Exod29:12\">EXO 29:12</a>, <a href=\"https://ref.ly/Exod29:12\">EXO 29:12</a>, <a href=\"https://ref.ly/Exod29:13\">EXO 29:13</a>, <a href=\"https://ref.ly/Exod29:16\">EXO 29:16</a>, <a href=\"https://ref.ly/Exod29:18\">EXO 29:18</a>, <a href=\"https://ref.ly/Exod29:20\">EXO 29:20</a>, <a href=\"https://ref.ly/Exod29:21\">EXO 29:21</a>, <a href=\"https://ref.ly/Exod29:25\">EXO 29:25</a>, <a href=\"https://ref.ly/Exod29:36\">EXO 29:36</a>, <a href=\"https://ref.ly/Exod29:37\">EXO 29:37</a>, <a href=\"https://ref.ly/Exod29:37\">EXO 29:37</a>, <a href=\"https://ref.ly/Exod29:37\">EXO 29:37</a>, <a href=\"https://ref.ly/Exod29:38\">EXO 29:38</a>, <a href=\"https://ref.ly/Exod29:44\">EXO 29:44</a>, <a href=\"https://ref.ly/Exod30:18\">EXO 30:18</a>, <a href=\"https://ref.ly/Exod30:20\">EXO 30:20</a>, <a href=\"https://ref.ly/Exod30:28\">EXO 30:28</a>, <a href=\"https://ref.ly/Exod31:9\">EXO 31:9</a>, <a href=\"https://ref.ly/Exod35:16\">EXO 35:16</a>, <a href=\"https://ref.ly/Exod38:1\">EXO 38:1</a>, <a href=\"https://ref.ly/Exod38:3\">EXO 38:3</a>, <a href=\"https://ref.ly/Exod38:4\">EXO 38:4</a>, <a href=\"https://ref.ly/Exod38:7\">EXO 38:7</a>, <a href=\"https://ref.ly/Exod38:30\">EXO 38:30</a>, <a href=\"https://ref.ly/Exod38:30\">EXO 38:30</a>, <a href=\"https://ref.ly/Exod39:39\">EXO 39:39</a>, <a href=\"https://ref.ly/Exod40:6\">EXO 40:6</a>, <a href=\"https://ref.ly/Exod40:7\">EXO 40:7</a>, <a href=\"https://ref.ly/Exod40:10\">EXO 40:10</a>, <a href=\"https://ref.ly/Exod40:10\">EXO 40:10</a>, <a href=\"https://ref.ly/Exod40:10\">EXO 40:10</a>, <a href=\"https://ref.ly/Exod40:29\">EXO 40:29</a>, <a href=\"https://ref.ly/Exod40:30\">EXO 40:30</a>, <a href=\"https://ref.ly/Exod40:32\">EXO 40:32</a>, <a href=\"https://ref.ly/Exod40:33\">EXO 40:33</a>, <a href=\"https://ref.ly/Lev1:5\">LEV 1:5</a>, <a href=\"https://ref.ly/Lev1:7\">LEV 1:7</a>, <a href=\"https://ref.ly/Lev1:8\">LEV 1:8</a>, <a href=\"https://ref.ly/Lev1:9\">LEV 1:9</a>, <a href=\"https://ref.ly/Lev1:11\">LEV 1:11</a>, <a href=\"https://ref.ly/Lev1:11\">LEV 1:11</a>, <a href=\"https://ref.ly/Lev1:12\">LEV 1:12</a>, <a href=\"https://ref.ly/Lev1:13\">LEV 1:13</a>, <a href=\"https://ref.ly/Lev1:15\">LEV 1:15</a>, <a href=\"https://ref.ly/Lev1:15\">LEV 1:15</a>, <a href=\"https://ref.ly/Lev1:15\">LEV 1:15</a>, <a href=\"https://ref.ly/Lev1:16\">LEV 1:16</a>, <a href=\"https://ref.ly/Lev1:17\">LEV 1:17</a>, <a href=\"https://ref.ly/Lev2:2\">LEV 2:2</a>, <a href=\"https://ref.ly/Lev2:8\">LEV 2:8</a>, <a href=\"https://ref.ly/Lev2:9\">LEV 2:9</a>, <a href=\"https://ref.ly/Lev2:12\">LEV 2:12</a>, <a href=\"https://ref.ly/Lev3:2\">LEV 3:2</a>, <a href=\"https://ref.ly/Lev3:5\">LEV 3:5</a>, <a href=\"https://ref.ly/Lev3:8\">LEV 3:8</a>, <a href=\"https://ref.ly/Lev3:11\">LEV 3:11</a>, <a href=\"https://ref.ly/Lev3:13\">LEV 3:13</a>, <a href=\"https://ref.ly/Lev3:16\">LEV 3:16</a>, <a href=\"https://ref.ly/Lev4:7\">LEV 4:7</a>, <a href=\"https://ref.ly/Lev4:10\">LEV 4:10</a>, <a href=\"https://ref.ly/Lev4:18\">LEV 4:18</a>, <a href=\"https://ref.ly/Lev4:18\">LEV 4:18</a>, <a href=\"https://ref.ly/Lev4:19\">LEV 4:19</a>, <a href=\"https://ref.ly/Lev4:25\">LEV 4:25</a>, <a href=\"https://ref.ly/Lev4:25\">LEV 4:25</a>, <a href=\"https://ref.ly/Lev4:26\">LEV 4:26</a>, <a href=\"https://ref.ly/Lev4:30\">LEV 4:30</a>, <a href=\"https://ref.ly/Lev4:30\">LEV 4:30</a>, <a href=\"https://ref.ly/Lev4:31\">LEV 4:31</a>, <a href=\"https://ref.ly/Lev4:34\">LEV 4:34</a>, <a href=\"https://ref.ly/Lev4:34\">LEV 4:34</a>, <a href=\"https://ref.ly/Lev4:35\">LEV 4:35</a>, <a href=\"https://ref.ly/Lev5:9\">LEV 5:9</a>, <a href=\"https://ref.ly/Lev5:9\">LEV 5:9</a>, <a href=\"https://ref.ly/Lev5:12\">LEV 5:12</a>, <a href=\"https://ref.ly/Lev6:2\">LEV 6:2</a>, <a href=\"https://ref.ly/Lev6:2\">LEV 6:2</a>, <a href=\"https://ref.ly/Lev6:3\">LEV 6:3</a>, <a href=\"https://ref.ly/Lev6:3\">LEV 6:3</a>, <a href=\"https://ref.ly/Lev6:5\">LEV 6:5</a>, <a href=\"https://ref.ly/Lev6:6\">LEV 6:6</a>, <a href=\"https://ref.ly/Lev6:7\">LEV 6:7</a>, <a href=\"https://ref.ly/Lev6:8\">LEV 6:8</a>, <a href=\"https://ref.ly/Lev7:2\">LEV 7:2</a>, <a href=\"https://ref.ly/Lev7:5\">LEV 7:5</a>, <a href=\"https://ref.ly/Lev7:31\">LEV 7:31</a>, <a href=\"https://ref.ly/Lev8:11\">LEV 8:11</a>, <a href=\"https://ref.ly/Lev8:11\">LEV 8:11</a>, <a href=\"https://ref.ly/Lev8:15\">LEV 8:15</a>, <a href=\"https://ref.ly/Lev8:15\">LEV 8:15</a>, <a href=\"https://ref.ly/Lev8:15\">LEV 8:15</a>, <a href=\"https://ref.ly/Lev8:16\">LEV 8:16</a>, <a href=\"https://ref.ly/Lev8:19\">LEV 8:19</a>, <a href=\"https://ref.ly/Lev8:21\">LEV 8:21</a>, <a href=\"https://ref.ly/Lev8:24\">LEV 8:24</a>, <a href=\"https://ref.ly/Lev8:28\">LEV 8:28</a>, <a href=\"https://ref.ly/Lev8:30\">LEV 8:30</a>, <a href=\"https://ref.ly/Lev9:7\">LEV 9:7</a>, <a href=\"https://ref.ly/Lev9:8\">LEV 9:8</a>, <a href=\"https://ref.ly/Lev9:9\">LEV 9:9</a>, <a href=\"https://ref.ly/Lev9:9\">LEV 9:9</a>, <a href=\"https://ref.ly/Lev9:10\">LEV 9:10</a>, <a href=\"https://ref.ly/Lev9:12\">LEV 9:12</a>, <a href=\"https://ref.ly/Lev9:13\">LEV 9:13</a>, <a href=\"https://ref.ly/Lev9:14\">LEV 9:14</a>, <a href=\"https://ref.ly/Lev9:17\">LEV 9:17</a>, <a href=\"https://ref.ly/Lev9:18\">LEV 9:18</a>, <a href=\"https://ref.ly/Lev9:20\">LEV 9:20</a>, <a href=\"https://ref.ly/Lev9:24\">LEV 9:24</a>, <a href=\"https://ref.ly/Lev10:12\">LEV 10:12</a>, <a href=\"https://ref.ly/Lev14:20\">LEV 14:20</a>, <a href=\"https://ref.ly/Lev16:12\">LEV 16:12</a>, <a href=\"https://ref.ly/Lev16:18\">LEV 16:18</a>, <a href=\"https://ref.ly/Lev16:18\">LEV 16:18</a>, <a href=\"https://ref.ly/Lev16:20\">LEV 16:20</a>, <a href=\"https://ref.ly/Lev16:25\">LEV 16:25</a>, <a href=\"https://ref.ly/Lev16:33\">LEV 16:33</a>, <a href=\"https://ref.ly/Lev17:6\">LEV 17:6</a>, <a href=\"https://ref.ly/Lev17:11\">LEV 17:11</a>, <a href=\"https://ref.ly/Lev21:23\">LEV 21:23</a>, <a href=\"https://ref.ly/Lev22:22\">LEV 22:22</a>, <a href=\"https://ref.ly/Num3:26\">NUM 3:26</a>, <a href=\"https://ref.ly/Num3:31\">NUM 3:31</a>, <a href=\"https://ref.ly/Num4:13\">NUM 4:13</a>, <a href=\"https://ref.ly/Num4:14\">NUM 4:14</a>, <a href=\"https://ref.ly/Num4:26\">NUM 4:26</a>, <a href=\"https://ref.ly/Num5:25\">NUM 5:25</a>, <a href=\"https://ref.ly/Num5:26\">NUM 5:26</a>, <a href=\"https://ref.ly/Num7:1\">NUM 7:1</a>, <a href=\"https://ref.ly/Num7:10\">NUM 7:10</a>, <a href=\"https://ref.ly/Num7:10\">NUM 7:10</a>, <a href=\"https://ref.ly/Num7:11\">NUM 7:11</a>, <a href=\"https://ref.ly/Num7:84\">NUM 7:84</a>, <a href=\"https://ref.ly/Num7:88\">NUM 7:88</a>, <a href=\"https://ref.ly/Num17:3\">NUM 17:3</a>, <a href=\"https://ref.ly/Num17:4\">NUM 17:4</a>, <a href=\"https://ref.ly/Num17:11\">NUM 17:11</a>, <a href=\"https://ref.ly/Num18:3\">NUM 18:3</a>, <a href=\"https://ref.ly/Num18:5\">NUM 18:5</a>, <a href=\"https://ref.ly/Num18:7\">NUM 18:7</a>, <a href=\"https://ref.ly/Num18:17\">NUM 18:17</a>, <a href=\"https://ref.ly/Deut12:27\">DEU 12:27</a>, <a href=\"https://ref.ly/Deut12:27\">DEU 12:27</a>, <a href=\"https://ref.ly/Deut16:21\">DEU 16:21</a>, <a href=\"https://ref.ly/Deut26:4\">DEU 26:4</a>, <a href=\"https://ref.ly/Josh22:29\">JOS 22:29</a>, <a href=\"https://ref.ly/1Sam2:28\">1SA 2:28</a>, <a href=\"https://ref.ly/1Sam2:33\">1SA 2:33</a>, <a href=\"https://ref.ly/1Kgs1:50\">1KI 1:50</a>, <a href=\"https://ref.ly/1Kgs1:51\">1KI 1:51</a>, <a href=\"https://ref.ly/1Kgs1:53\">1KI 1:53</a>, <a href=\"https://ref.ly/1Kgs2:28\">1KI 2:28</a>, <a href=\"https://ref.ly/1Kgs2:29\">1KI 2:29</a>, <a href=\"https://ref.ly/1Chr21:29\">1CH 21:29</a>, <a href=\"https://ref.ly/2Chr1:5\">2CH 1:5</a>, <a href=\"https://ref.ly/2Chr1:6\">2CH 1:6</a></div>\n</div>\n</div>\n</div><div class=\"thlex-section\">\n<h2 class=\"thlex-heading\">References:</h2>\n<h3 class=\"thlex-subheading\">\n          <strong>Rim, ledge</strong>:</h3>\n<div class=\"thlex-language-sets\">\n<div class=\"thlex-language-set\">\n<span class=\"thlex-language\">Hebrew</span> <span class=\"thlex-lemma\">כַּרְכֹּב</span> <span class=\"thlex-translit\">(karkov)</span>\n<div class=\"thlex-refs\"><a href=\"https://ref.ly/Exod27:5\">EXO 27:5</a>, <a href=\"https://ref.ly/Exod38:4\">EXO 38:4</a></div>\n</div>\n</div>\n</div><div class=\"thlex-section\">\n<h2 class=\"thlex-heading\">Description:</h2>\n<div class=\"thlex-paragraphs\">\n<p>\n            <figure class=\"thlex-image\"><img class=\"thlex-img\" src=\"images/WEB-0444_tabernacle_altar.jpg\" alt=\"The altar of the movable tabernacle (Timnah Park model)\"><figcaption class=\"thlex-caption\">The altar of the movable tabernacle (Timnah Park model) (© Ori229, CC BY-SA 3.0, via Wikimedia Commons)</figcaption></figure>The Tabernacle altar was made of acacia wood overlaid, perhaps inside and out, with bronze. It measured five cubits (2.5 meters; 8.3 feet) on a side and stood three cubits (1.5 meters; 5 feet) high. Around its top was a kind of ledge or rim (<em>karkov</em> in Hebrew), the purpose of which is not given. The altar was hollow.</p>\n<hr/>\n</div>\n</div><div class=\"thlex-section\">\n<h2 class=\"thlex-heading\">Translation:</h2>\n<div class=\"thlex-paragraphs\">\n<p>See <a class=\"thlex-xref\" data-bnType=\"lexiconLink\" data-collection=\"\" data-key=\"\" href=\"#\">4.2 Altars&lt;REALIA:4.2&gt;</a> and <a class=\"thlex-xref\" data-bnType=\"lexiconLink\" data-collection=\"\" data-key=\"\" href=\"#\">4.2.1 Stone altar&lt;REALIA:4.2.1&gt;</a> above.</p>\n<p>\n            <strong>Rim, ledge</strong>: The Hebrew word <em>karkov</em> is found only in <a href=\"https://ref.ly/Exod27:5\">EXO 27:5</a> and <a href=\"https://ref.ly/Exod38:4\">EXO 38:4</a>, and its meaning is unclear. Some scholars think of it as a decorative “rim” (<abbr class=\"thlex-abbr\" title=\"Good News Translation (1992)\">GNT</abbr>) around the altar that could also support the weight of the altar when lifted by the rings on the grating (<a href=\"https://ref.ly/Exod27:4\">EXO 27:4</a>; see <a class=\"thlex-xref\" data-bnType=\"lexiconLink\" data-collection=\"\" data-key=\"\" href=\"#\">4.2.3 Temple altar&lt;REALIA:4.2.3&gt;</a> for an illustration of a rim). Others imagine that it may have been a “ledge” (<abbr class=\"thlex-abbr\" title=\"Revised Standard Version (1952)\">RSV</abbr>) wide enough for the officiating priests to stand on, but this is unlikely since the altar itself was only about 1.5 meters (5 feet) high.</p>\n<p>It is not clear whether this rim was at the top, the middle, or the bottom of the altar. Neither is it clear whether it was on the inside or the outside of the altar. <abbr class=\"thlex-abbr\" title=\"New American Bible (1970)\">NAB</abbr> translates <em>karkov</em> simply as “around,” since its root meaning may have been to surround or encircle. <a href=\"https://ref.ly/Exod27:5\">EXO 27:5</a> a in <abbr class=\"thlex-abbr\" title=\"New American Bible (1970)\">NAB</abbr> reads “Put it [the grating] down around the altar, on the ground.”</p>\n<p>Note that the Hebrew clause in <a href=\"https://ref.ly/Exod27:5\">EXO 27:5</a> uses both the words “under” and “below,” possibly for emphasis or clarity. <abbr class=\"thlex-abbr\" title=\"New Jewish Publication Society Version\">NJPSV</abbr> has “Set the mesh below, under the ledge of the altar,” and <abbr class=\"thlex-abbr\" title=\"New Jerusalem Bible (1985)\">NJB</abbr> says “You will put it below the ledge of the altar, underneath.” Since there is so much uncertainty about the meaning of these terms, translators must choose either the idea of a “ledge” or a “rim.” We may assume that it was a structural rim located probably around the top of the altar.</p>\n</div>\n</div>",
"associations": {
"passage": [
{
"start_ref": "02027001",
"start_ref_usfm": "EXO 27:1",
"end_ref": "02027001",
"end_ref_usfm": "EXO 27:1"
},
{
"start_ref": "02027005",
"start_ref_usfm": "EXO 27:5",
"end_ref": "02027005",
"end_ref_usfm": "EXO 27:5"
},
{
"start_ref": "02027006",
"start_ref_usfm": "EXO 27:6",
"end_ref": "02027006",
"end_ref_usfm": "EXO 27:6"
},
{
"start_ref": "02027007",
"start_ref_usfm": "EXO 27:7",
"end_ref": "02027007",
"end_ref_usfm": "EXO 27:7"
},
{
"start_ref": "02028043",
"start_ref_usfm": "EXO 28:43",
"end_ref": "02028043",
"end_ref_usfm": "EXO 28:43"
},
{
"start_ref": "02029012",
"start_ref_usfm": "EXO 29:12",
"end_ref": "02029012",
"end_ref_usfm": "EXO 29:12"
},
{
"start_ref": "02029013",
"start_ref_usfm": "EXO 29:13",
"end_ref": "02029013",
"end_ref_usfm": "EXO 29:13"
},
{
"start_ref": "02029016",
"start_ref_usfm": "EXO 29:16",
"end_ref": "02029016",
"end_ref_usfm": "EXO 29:16"
},
{
"start_ref": "02029018",
"start_ref_usfm": "EXO 29:18",
"end_ref": "02029018",
"end_ref_usfm": "EXO 29:18"
},
{
"start_ref": "02029020",
"start_ref_usfm": "EXO 29:20",
"end_ref": "02029020",
"end_ref_usfm": "EXO 29:20"
},
{
"start_ref": "02029021",
"start_ref_usfm": "EXO 29:21",
"end_ref": "02029021",
"end_ref_usfm": "EXO 29:21"
},
{
"start_ref": "02029025",
"start_ref_usfm": "EXO 29:25",
"end_ref": "02029025",
"end_ref_usfm": "EXO 29:25"
},
{
"start_ref": "02029036",
"start_ref_usfm": "EXO 29:36",
"end_ref": "02029036",
"end_ref_usfm": "EXO 29:36"
},
{
"start_ref": "02029037",
"start_ref_usfm": "EXO 29:37",
"end_ref": "02029037",
"end_ref_usfm": "EXO 29:37"
},
{
"start_ref": "02029038",
"start_ref_usfm": "EXO 29:38",
"end_ref": "02029038",
"end_ref_usfm": "EXO 29:38"
},
{
"start_ref": "02029044",
"start_ref_usfm": "EXO 29:44",
"end_ref": "02029044",
"end_ref_usfm": "EXO 29:44"
},
{
"start_ref": "02030018",
"start_ref_usfm": "EXO 30:18",
"end_ref": "02030018",
"end_ref_usfm": "EXO 30:18"
},
{
"start_ref": "02030020",
"start_ref_usfm": "EXO 30:20",
"end_ref": "02030020",
"end_ref_usfm": "EXO 30:20"
},
{
"start_ref": "02030028",
"start_ref_usfm": "EXO 30:28",
"end_ref": "02030028",
"end_ref_usfm": "EXO 30:28"
},
{
"start_ref": "02031009",
"start_ref_usfm": "EXO 31:9",
"end_ref": "02031009",
"end_ref_usfm": "EXO 31:9"
},
{
"start_ref": "02035016",
"start_ref_usfm": "EXO 35:16",
"end_ref": "02035016",
"end_ref_usfm": "EXO 35:16"
},
{
"start_ref": "02038001",
"start_ref_usfm": "EXO 38:1",
"end_ref": "02038001",
"end_ref_usfm": "EXO 38:1"
},
{
"start_ref": "02038003",
"start_ref_usfm": "EXO 38:3",
"end_ref": "02038003",
"end_ref_usfm": "EXO 38:3"
},
{
"start_ref": "02038004",
"start_ref_usfm": "EXO 38:4",
"end_ref": "02038004",
"end_ref_usfm": "EXO 38:4"
},
{
"start_ref": "02038007",
"start_ref_usfm": "EXO 38:7",
"end_ref": "02038007",
"end_ref_usfm": "EXO 38:7"
},
{
"start_ref": "02038030",
"start_ref_usfm": "EXO 38:30",
"end_ref": "02038030",
"end_ref_usfm": "EXO 38:30"
},
{
"start_ref": "02039039",
"start_ref_usfm": "EXO 39:39",
"end_ref": "02039039",
"end_ref_usfm": "EXO 39:39"
},
{
"start_ref": "02040006",
"start_ref_usfm": "EXO 40:6",
"end_ref": "02040006",
"end_ref_usfm": "EXO 40:6"
},
{
"start_ref": "02040007",
"start_ref_usfm": "EXO 40:7",
"end_ref": "02040007",
"end_ref_usfm": "EXO 40:7"
},
{
"start_ref": "02040010",
"start_ref_usfm": "EXO 40:10",
"end_ref": "02040010",
"end_ref_usfm": "EXO 40:10"
},
{
"start_ref": "02040029",
"start_ref_usfm": "EXO 40:29",
"end_ref": "02040029",
"end_ref_usfm": "EXO 40:29"
},
{
"start_ref": "02040030",
"start_ref_usfm": "EXO 40:30",
"end_ref": "02040030",
"end_ref_usfm": "EXO 40:30"
},
{
"start_ref": "02040032",
"start_ref_usfm": "EXO 40:32",
"end_ref": "02040032",
"end_ref_usfm": "EXO 40:32"
},
{
"start_ref": "02040033",
"start_ref_usfm": "EXO 40:33",
"end_ref": "02040033",
"end_ref_usfm": "EXO 40:33"
},
{
"start_ref": "03001005",
"start_ref_usfm": "LEV 1:5",
"end_ref": "03001005",
"end_ref_usfm": "LEV 1:5"
},
{
"start_ref": "03001007",
"start_ref_usfm": "LEV 1:7",
"end_ref": "03001007",
"end_ref_usfm": "LEV 1:7"
},
{
"start_ref": "03001008",
"start_ref_usfm": "LEV 1:8",
"end_ref": "03001008",
"end_ref_usfm": "LEV 1:8"
},
{
"start_ref": "03001009",
"start_ref_usfm": "LEV 1:9",
"end_ref": "03001009",
"end_ref_usfm": "LEV 1:9"
},
{
"start_ref": "03001011",
"start_ref_usfm": "LEV 1:11",
"end_ref": "03001011",
"end_ref_usfm": "LEV 1:11"
},
{
"start_ref": "03001012",
"start_ref_usfm": "LEV 1:12",
"end_ref": "03001012",
"end_ref_usfm": "LEV 1:12"
},
{
"start_ref": "03001013",
"start_ref_usfm": "LEV 1:13",
"end_ref": "03001013",
"end_ref_usfm": "LEV 1:13"
},
{
"start_ref": "03001015",
"start_ref_usfm": "LEV 1:15",
"end_ref": "03001015",
"end_ref_usfm": "LEV 1:15"
},
{
"start_ref": "03001016",
"start_ref_usfm": "LEV 1:16",
"end_ref": "03001016",
"end_ref_usfm": "LEV 1:16"
},
{
"start_ref": "03001017",
"start_ref_usfm": "LEV 1:17",
"end_ref": "03001017",
"end_ref_usfm": "LEV 1:17"
},
{
"start_ref": "03002002",
"start_ref_usfm": "LEV 2:2",
"end_ref": "03002002",
"end_ref_usfm": "LEV 2:2"
},
{
"start_ref": "03002008",
"start_ref_usfm": "LEV 2:8",
"end_ref": "03002008",
"end_ref_usfm": "LEV 2:8"
},
{
"start_ref": "03002009",
"start_ref_usfm": "LEV 2:9",
"end_ref": "03002009",
"end_ref_usfm": "LEV 2:9"
},
{
"start_ref": "03002012",
"start_ref_usfm": "LEV 2:12",
"end_ref": "03002012",
"end_ref_usfm": "LEV 2:12"
},
{
"start_ref": "03003002",
"start_ref_usfm": "LEV 3:2",
"end_ref": "03003002",
"end_ref_usfm": "LEV 3:2"
},
{
"start_ref": "03003005",
"start_ref_usfm": "LEV 3:5",
"end_ref": "03003005",
"end_ref_usfm": "LEV 3:5"
},
{
"start_ref": "03003008",
"start_ref_usfm": "LEV 3:8",
"end_ref": "03003008",
"end_ref_usfm": "LEV 3:8"
},
{
"start_ref": "03003011",
"start_ref_usfm": "LEV 3:11",
"end_ref": "03003011",
"end_ref_usfm": "LEV 3:11"
},
{
"start_ref": "03003013",
"start_ref_usfm": "LEV 3:13",
"end_ref": "03003013",
"end_ref_usfm": "LEV 3:13"
},
{
"start_ref": "03003016",
"start_ref_usfm": "LEV 3:16",
"end_ref": "03003016",
"end_ref_usfm": "LEV 3:16"
},
{
"start_ref": "03004007",
"start_ref_usfm": "LEV 4:7",
"end_ref": "03004007",
"end_ref_usfm": "LEV 4:7"
},
{
"start_ref": "03004010",
"start_ref_usfm": "LEV 4:10",
"end_ref": "03004010",
"end_ref_usfm": "LEV 4:10"
},
{
"start_ref": "03004018",
"start_ref_usfm": "LEV 4:18",
"end_ref": "03004018",
"end_ref_usfm": "LEV 4:18"
},
{
"start_ref": "03004019",
"start_ref_usfm": "LEV 4:19",
"end_ref": "03004019",
"end_ref_usfm": "LEV 4:19"
},
{
"start_ref": "03004025",
"start_ref_usfm": "LEV 4:25",
"end_ref": "03004025",
"end_ref_usfm": "LEV 4:25"
},
{
"start_ref": "03004026",
"start_ref_usfm": "LEV 4:26",
"end_ref": "03004026",
"end_ref_usfm": "LEV 4:26"
},
{
"start_ref": "03004030",
"start_ref_usfm": "LEV 4:30",
"end_ref": "03004030",
"end_ref_usfm": "LEV 4:30"
},
{
"start_ref": "03004031",
"start_ref_usfm": "LEV 4:31",
"end_ref": "03004031",
"end_ref_usfm": "LEV 4:31"
},
{
"start_ref": "03004034",
"start_ref_usfm": "LEV 4:34",
"end_ref": "03004034",
"end_ref_usfm": "LEV 4:34"
},
{
"start_ref": "03004035",
"start_ref_usfm": "LEV 4:35",
"end_ref": "03004035",
"end_ref_usfm": "LEV 4:35"
},
{
"start_ref": "03005009",
"start_ref_usfm": "LEV 5:9",
"end_ref": "03005009",
"end_ref_usfm": "LEV 5:9"
},
{
"start_ref": "03005012",
"start_ref_usfm": "LEV 5:12",
"end_ref": "03005012",
"end_ref_usfm": "LEV 5:12"
},
{
"start_ref": "03006002",
"start_ref_usfm": "LEV 6:2",
"end_ref": "03006002",
"end_ref_usfm": "LEV 6:2"
},
{
"start_ref": "03006003",
"start_ref_usfm": "LEV 6:3",
"end_ref": "03006003",
"end_ref_usfm": "LEV 6:3"
},
{
"start_ref": "03006005",
"start_ref_usfm": "LEV 6:5",
"end_ref": "03006005",
"end_ref_usfm": "LEV 6:5"
},
{
"start_ref": "03006006",
"start_ref_usfm": "LEV 6:6",
"end_ref": "03006006",
"end_ref_usfm": "LEV 6:6"
},
{
"start_ref": "03006007",
"start_ref_usfm": "LEV 6:7",
"end_ref": "03006007",
"end_ref_usfm": "LEV 6:7"
},
{
"start_ref": "03006008",
"start_ref_usfm": "LEV 6:8",
"end_ref": "03006008",
"end_ref_usfm": "LEV 6:8"
},
{
"start_ref": "03007002",
"start_ref_usfm": "LEV 7:2",
"end_ref": "03007002",
"end_ref_usfm": "LEV 7:2"
},
{
"start_ref": "03007005",
"start_ref_usfm": "LEV 7:5",
"end_ref": "03007005",
"end_ref_usfm": "LEV 7:5"
},
{
"start_ref": "03007031",
"start_ref_usfm": "LEV 7:31",
"end_ref": "03007031",
"end_ref_usfm": "LEV 7:31"
},
{
"start_ref": "03008011",
"start_ref_usfm": "LEV 8:11",
"end_ref": "03008011",
"end_ref_usfm": "LEV 8:11"
},
{
"start_ref": "03008015",
"start_ref_usfm": "LEV 8:15",
"end_ref": "03008015",
"end_ref_usfm": "LEV 8:15"
},
{
"start_ref": "03008016",
"start_ref_usfm": "LEV 8:16",
"end_ref": "03008016",
"end_ref_usfm": "LEV 8:16"
},
{
"start_ref": "03008019",
"start_ref_usfm": "LEV 8:19",
"end_ref": "03008019",
"end_ref_usfm": "LEV 8:19"
},
{
"start_ref": "03008021",
"start_ref_usfm": "LEV 8:21",
"end_ref": "03008021",
"end_ref_usfm": "LEV 8:21"
},
{
"start_ref": "03008024",
"start_ref_usfm": "LEV 8:24",
"end_ref": "03008024",
"end_ref_usfm": "LEV 8:24"
},
{
"start_ref": "03008028",
"start_ref_usfm": "LEV 8:28",
"end_ref": "03008028",
"end_ref_usfm": "LEV 8:28"
},
{
"start_ref": "03008030",
"start_ref_usfm": "LEV 8:30",
"end_ref": "03008030",
"end_ref_usfm": "LEV 8:30"
},
{
"start_ref": "03009007",
"start_ref_usfm": "LEV 9:7",
"end_ref": "03009007",
"end_ref_usfm": "LEV 9:7"
},
{
"start_ref": "03009008",
"start_ref_usfm": "LEV 9:8",
"end_ref": "03009008",
"end_ref_usfm": "LEV 9:8"
},
{
"start_ref": "03009009",
"start_ref_usfm": "LEV 9:9",
"end_ref": "03009009",
"end_ref_usfm": "LEV 9:9"
},
{
"start_ref": "03009010",
"start_ref_usfm": "LEV 9:10",
"end_ref": "03009010",
"end_ref_usfm": "LEV 9:10"
},
{
"start_ref": "03009012",
"start_ref_usfm": "LEV 9:12",
"end_ref": "03009012",
"end_ref_usfm": "LEV 9:12"
},
{
"start_ref": "03009013",
"start_ref_usfm": "LEV 9:13",
"end_ref": "03009013",
"end_ref_usfm": "LEV 9:13"
},
{
"start_ref": "03009014",
"start_ref_usfm": "LEV 9:14",
"end_ref": "03009014",
"end_ref_usfm": "LEV 9:14"
},
{
"start_ref": "03009017",
"start_ref_usfm": "LEV 9:17",
"end_ref": "03009017",
"end_ref_usfm": "LEV 9:17"
},
{
"start_ref": "03009018",
"start_ref_usfm": "LEV 9:18",
"end_ref": "03009018",
"end_ref_usfm": "LEV 9:18"
},
{
"start_ref": "03009020",
"start_ref_usfm": "LEV 9:20",
"end_ref": "03009020",
"end_ref_usfm": "LEV 9:20"
},
{
"start_ref": "03009024",
"start_ref_usfm": "LEV 9:24",
"end_ref": "03009024",
"end_ref_usfm": "LEV 9:24"
},
{
"start_ref": "03010012",
"start_ref_usfm": "LEV 10:12",
"end_ref": "03010012",
"end_ref_usfm": "LEV 10:12"
},
{
"start_ref": "03014020",
"start_ref_usfm": "LEV 14:20",
"end_ref": "03014020",
"end_ref_usfm": "LEV 14:20"
},
{
"start_ref": "03016012",
"start_ref_usfm": "LEV 16:12",
"end_ref": "03016012",
"end_ref_usfm": "LEV 16:12"
},
{
"start_ref": "03016018",
"start_ref_usfm": "LEV 16:18",
"end_ref": "03016018",
"end_ref_usfm": "LEV 16:18"
},
{
"start_ref": "03016020",
"start_ref_usfm": "LEV 16:20",
"end_ref": "03016020",
"end_ref_usfm": "LEV 16:20"
},
{
"start_ref": "03016025",
"start_ref_usfm": "LEV 16:25",
"end_ref": "03016025",
"end_ref_usfm": "LEV 16:25"
},
{
"start_ref": "03016033",
"start_ref_usfm": "LEV 16:33",
"end_ref": "03016033",
"end_ref_usfm": "LEV 16:33"
},
{
"start_ref": "03017006",
"start_ref_usfm": "LEV 17:6",
"end_ref": "03017006",
"end_ref_usfm": "LEV 17:6"
},
{
"start_ref": "03017011",
"start_ref_usfm": "LEV 17:11",
"end_ref": "03017011",
"end_ref_usfm": "LEV 17:11"
},
{
"start_ref": "03021023",
"start_ref_usfm": "LEV 21:23",
"end_ref": "03021023",
"end_ref_usfm": "LEV 21:23"
},
{
"start_ref": "03022022",
"start_ref_usfm": "LEV 22:22",
"end_ref": "03022022",
"end_ref_usfm": "LEV 22:22"
},
{
"start_ref": "04003026",
"start_ref_usfm": "NUM 3:26",
"end_ref": "04003026",
"end_ref_usfm": "NUM 3:26"
},
{
"start_ref": "04003031",
"start_ref_usfm": "NUM 3:31",
"end_ref": "04003031",
"end_ref_usfm": "NUM 3:31"
},
{
"start_ref": "04004013",
"start_ref_usfm": "NUM 4:13",
"end_ref": "04004013",
"end_ref_usfm": "NUM 4:13"
},
{
"start_ref": "04004014",
"start_ref_usfm": "NUM 4:14",
"end_ref": "04004014",
"end_ref_usfm": "NUM 4:14"
},
{
"start_ref": "04004026",
"start_ref_usfm": "NUM 4:26",
"end_ref": "04004026",
"end_ref_usfm": "NUM 4:26"
},
{
"start_ref": "04005025",
"start_ref_usfm": "NUM 5:25",
"end_ref": "04005025",
"end_ref_usfm": "NUM 5:25"
},
{
"start_ref": "04005026",
"start_ref_usfm": "NUM 5:26",
"end_ref": "04005026",
"end_ref_usfm": "NUM 5:26"
},
{
"start_ref": "04007001",
"start_ref_usfm": "NUM 7:1",
"end_ref": "04007001",
"end_ref_usfm": "NUM 7:1"
},
{
"start_ref": "04007010",
"start_ref_usfm": "NUM 7:10",
"end_ref": "04007010",
"end_ref_usfm": "NUM 7:10"
},
{
"start_ref": "04007011",
"start_ref_usfm": "NUM 7:11",
"end_ref": "04007011",
"end_ref_usfm": "NUM 7:11"
},
{
"start_ref": "04007084",
"start_ref_usfm": "NUM 7:84",
"end_ref": "04007084",
"end_ref_usfm": "NUM 7:84"
},
{
"start_ref": "04007088",
"start_ref_usfm": "NUM 7:88",
"end_ref": "04007088",
"end_ref_usfm": "NUM 7:88"
},
{
"start_ref": "04017003",
"start_ref_usfm": "NUM 17:3",
"end_ref": "04017003",
"end_ref_usfm": "NUM 17:3"
},
{
"start_ref": "04017004",
"start_ref_usfm": "NUM 17:4",
"end_ref": "04017004",
"end_ref_usfm": "NUM 17:4"
},
{
"start_ref": "04017011",
"start_ref_usfm": "NUM 17:11",
"end_ref": "04017011",
"end_ref_usfm": "NUM 17:11"
},
{
"start_ref": "04018003",
"start_ref_usfm": "NUM 18:3",
"end_ref": "04018003",
"end_ref_usfm": "NUM 18:3"
},
{
"start_ref": "04018005",
"start_ref_usfm": "NUM 18:5",
"end_ref": "04018005",
"end_ref_usfm": "NUM 18:5"
},
{
"start_ref": "04018007",
"start_ref_usfm": "NUM 18:7",
"end_ref": "04018007",
"end_ref_usfm": "NUM 18:7"
},
{
"start_ref": "04018017",
"start_ref_usfm": "NUM 18:17",
"end_ref": "04018017",
"end_ref_usfm": "NUM 18:17"
},
{
"start_ref": "05012027",
"start_ref_usfm": "DEU 12:27",
"end_ref": "05012027",
"end_ref_usfm": "DEU 12:27"
},
{
"start_ref": "05016021",
"start_ref_usfm": "DEU 16:21",
"end_ref": "05016021",
"end_ref_usfm": "DEU 16:21"
},
{
"start_ref": "05026004",
"start_ref_usfm": "DEU 26:4",
"end_ref": "05026004",
"end_ref_usfm": "DEU 26:4"
},
{
"start_ref": "06022029",
"start_ref_usfm": "JOS 22:29",
"end_ref": "06022029",
"end_ref_usfm": "JOS 22:29"
},
{
"start_ref": "09002028",
"start_ref_usfm": "1SA 2:28",
"end_ref": "09002028",
"end_ref_usfm": "1SA 2:28"
},
{
"start_ref": "09002033",
"start_ref_usfm": "1SA 2:33",
"end_ref": "09002033",
"end_ref_usfm": "1SA 2:33"
},
{
"start_ref": "11001050",
"start_ref_usfm": "1KI 1:50",
"end_ref": "11001050",
"end_ref_usfm": "1KI 1:50"
},
{
"start_ref": "11001051",
"start_ref_usfm": "1KI 1:51",
"end_ref": "11001051",
"end_ref_usfm": "1KI 1:51"
},
{
"start_ref": "11001053",
"start_ref_usfm": "1KI 1:53",
"end_ref": "11001053",
"end_ref_usfm": "1KI 1:53"
},
{
"start_ref": "11002028",
"start_ref_usfm": "1KI 2:28",
"end_ref": "11002028",
"end_ref_usfm": "1KI 2:28"
},
{
"start_ref": "11002029",
"start_ref_usfm": "1KI 2:29",
"end_ref": "11002029",
"end_ref_usfm": "1KI 2:29"
},
{
"start_ref": "13021029",
"start_ref_usfm": "1CH 21:29",
"end_ref": "13021029",
"end_ref_usfm": "1CH 21:29"
},
{
"start_ref": "14001005",
"start_ref_usfm": "2CH 1:5",
"end_ref": "14001005",
"end_ref_usfm": "2CH 1:5"
},
{
"start_ref": "14001006",
"start_ref_usfm": "2CH 1:6",
"end_ref": "14001006",
"end_ref_usfm": "2CH 1:6"
},
{
"start_ref": "02027004",
"start_ref_usfm": "EXO 27:4",
"end_ref": "02027004",
"end_ref_usfm": "EXO 27:4"
}
],
"resource": []
}
},
{
"content_id": "REALIA:4.2.2.1",
"reference_id": "REALIA:4.2.2.1",
"version": "1.0.4",
"title": "Grating, mesh",
"media_type": "Text",
"index_reference": "4.2.2.1",
"language": "eng",
"review_level": "None",
"content": "<style>\nh1.thlex-title { font-size: 1.3em; margin: 0 0 0.4em; }\n.thlex-key { color: #888; font-size: 0.85em; font-weight: normal; margin-right: 0.4em; }\nnav.thlex-index { margin: 0.5em 0 0.75em; }\nnav.thlex-index ul { margin: 0; padding-left: 1.2em; }\nnav.thlex-index li { margin: 0.15em 0; font-size: 0.95em; }\n.thlex-section { margin: 0.6em 0; }\nh2.thlex-heading { font-size: 1em; margin: 0.5em 0 0.2em; }\nh3.thlex-subheading { font-size: 0.95em; font-weight: normal; font-style: italic; margin: 0.2em 0; }\n.thlex-language-sets { margin: 0.3em 0 0.3em 1em; }\n.thlex-language-set { margin: 0.4em 0; padding-left: 0.75em; border-left: 3px solid #e0e0e0; }\n.thlex-language { font-size: 0.8em; color: #888; margin-right: 0.4em; }\n.thlex-lemma { font-weight: bold; font-family: serif; }\n.thlex-translit { color: #555; font-style: italic; font-size: 0.9em; margin-left: 0.3em; }\n.thlex-refs { font-size: 0.85em; color: #444; margin-top: 0.15em; }\n.thlex-paragraphs p { margin: 0.35em 0; font-size: 0.95em; line-height: 1.5; }\n.thlex-image { margin: 0.5em 0; display: block; }\n.thlex-image img { max-width: 100%; height: auto; display: block; }\nfigcaption.thlex-caption { font-size: 0.85em; color: #555; font-style: italic; margin-top: 0.2em; }\n.thlex-abbr { border-bottom: 1px dotted #888; cursor: help; }\n.thlex-xref { color: #1a5fb4; }\nspan[data-bnType=\"bibleReference\"] { color: #1a5fb4; }\ntable.thlex-table { border-collapse: collapse; font-size: 0.9em; margin: 0.5em 0; }\ntable.thlex-table td { padding: 0.2em 0.6em; vertical-align: top; border: 1px solid #ddd; }\ntable.thlex-table tr:first-child td { font-weight: bold; background: #f5f5f5; }\nul.thlex-index-list { margin: 0.4em 0; padding-left: 1.4em; font-size: 0.95em; line-height: 1.6; }\nul.thlex-index-list ul { margin: 0.1em 0; padding-left: 1.4em; }\n.thlex-index-key { font-weight: bold; font-style: italic; }\n</style><h1 class=\"thlex-title\" id=\"REALIA:4.2.2.1\"><span class=\"thlex-key\">4.2.2.1</span> Grating, mesh</h1><div class=\"thlex-section\">\n<h2 class=\"thlex-heading\">References:</h2>\n<div class=\"thlex-language-sets\">\n<div class=\"thlex-language-set\">\n<span class=\"thlex-language\">Hebrew</span> <span class=\"thlex-lemma\">מִכְבָּר</span> <span class=\"thlex-translit\">(mikbar)</span>\n<div class=\"thlex-refs\"><a href=\"https://ref.ly/Exod27:4\">EXO 27:4</a>, <a href=\"https://ref.ly/Exod35:16\">EXO 35:16</a>, <a href=\"https://ref.ly/Exod38:5\">EXO 38:5</a>, <a href=\"https://ref.ly/Exod38:5\">EXO 38:5</a>, <a href=\"https://ref.ly/Exod38:30\">EXO 38:30</a>, <a href=\"https://ref.ly/Exod39:39\">EXO 39:39</a></div>\n</div>\n</div>\n</div><div class=\"thlex-section\">\n<h2 class=\"thlex-heading\">References:</h2>\n<h3 class=\"thlex-subheading\">\n          <strong>Ring</strong>:</h3>\n<div class=\"thlex-language-sets\">\n<div class=\"thlex-language-set\">\n<span class=\"thlex-language\">Hebrew</span> <span class=\"thlex-lemma\">טַבַּעַת</span> <span class=\"thlex-translit\">(taba‘ath)</span>\n<div class=\"thlex-refs\"><a href=\"https://ref.ly/Exod27:4\">EXO 27:4</a>, <a href=\"https://ref.ly/Exod27:7\">EXO 27:7</a>, <a href=\"https://ref.ly/Exod38:5\">EXO 38:5</a>, <a href=\"https://ref.ly/Exod38:7\">EXO 38:7</a></div>\n</div>\n</div>\n</div><div class=\"thlex-section\">\n<h2 class=\"thlex-heading\">References:</h2>\n<h3 class=\"thlex-subheading\">\n          <strong>Pole</strong>:</h3>\n<div class=\"thlex-language-sets\">\n<div class=\"thlex-language-set\">\n<span class=\"thlex-language\">Hebrew</span> <span class=\"thlex-lemma\">בַּד</span> <span class=\"thlex-translit\">(bad)</span>\n<div class=\"thlex-refs\"><a href=\"https://ref.ly/Exod27:6\">EXO 27:6</a>, <a href=\"https://ref.ly/Exod27:6\">EXO 27:6</a>, <a href=\"https://ref.ly/Exod27:7\">EXO 27:7</a>, <a href=\"https://ref.ly/Exod27:7\">EXO 27:7</a>, <a href=\"https://ref.ly/Exod38:5\">EXO 38:5</a>, <a href=\"https://ref.ly/Exod38:6\">EXO 38:6</a>, <a href=\"https://ref.ly/Exod38:7\">EXO 38:7</a></div>\n</div>\n</div>\n</div><div class=\"thlex-section\">\n<h2 class=\"thlex-heading\">Description and usage:</h2>\n<div class=\"thlex-paragraphs\">\n<p>\n            <figure class=\"thlex-image\"><img class=\"thlex-img\" src=\"images/WEB-0445_grating_en.png\" alt=\"Drawing of grating attached to the altar\"><figcaption class=\"thlex-caption\">Drawing of grating attached to the altar (Don Ellens, The Tabernacle of Israel, Harris, Jones 1888, Public domain)</figcaption></figure>The grating of the Tabernacle altar was similar to a spider’s web with a fine meshwork, except that it was made of bronze. Its purpose is not explained, but it was probably intended to hold the burning coals and allow the ashes and grease to fall through to the ground, as well as to allow for a draft of air to pass through from underneath. Both were necessary for a hot fire. On the four upper corners of the grating were attached bronze rings. Poles were inserted through these rings for transporting the altar.</p>\n<hr/>\n</div>\n</div><div class=\"thlex-section\">\n<h2 class=\"thlex-heading\">Translation:</h2>\n<div class=\"thlex-paragraphs\">\n<p>\n            <figure class=\"thlex-image\"><img class=\"thlex-img\" src=\"images/WEB-0446_grating.jpg\" alt=\"Grating inside the altar (BYU model)\"><figcaption class=\"thlex-caption\">Grating inside the altar (BYU model) (© Ben P L, CC BY 2.0, via Wikimedia Commons)</figcaption></figure>The Hebrew word for grating (<em>mikbar</em>) is related to the word for “sieve” in <a href=\"https://ref.ly/Amos9:9\">AMO 9:9</a>. The Hebrew phrase that describes it in <a href=\"https://ref.ly/Exod27:4\">EXO 27:4</a> is <em>ma‘aseh resheth</em>, which is literally “net-work.” The exact position and function of this mesh are disputed. Some scholars have suggested that it was simply wrapped around the bottom half of the altar as a decoration, perhaps also serving to strengthen the wooden frame of the altar; for example, <abbr class=\"thlex-abbr\" title=\"Contemporary English Version\">CEV</abbr> renders <a href=\"https://ref.ly/Exod27:4\">EXO 27:4</a> a as “cover the bottom half of the altar with a decorative bronze grating.” Most, however, understand it as it is described above. Its placement on or in the altar was related in some way to the rim or ledge, which went around the top of the altar (see <a class=\"thlex-xref\" data-bnType=\"lexiconLink\" data-collection=\"\" data-key=\"\" href=\"#\">4.2.2 Tabernacle altar&lt;REALIA:4.2.2&gt;</a>).</p>\n<p>“So that the net shall extend halfway down the altar” (<a href=\"https://ref.ly/Exod27:5\">EXO 27:5</a> b in <abbr class=\"thlex-abbr\" title=\"Revised Standard Version (1952)\">RSV</abbr>) is literally “and the net will be until half of the altar.” This does not indicate whether it means halfway down or “halfway up the altar” (<abbr class=\"thlex-abbr\" title=\"Good News Translation (1992)\">GNT</abbr>). Most translations have “halfway up,” suggesting that the grating was placed in some way at the lower half of the altar. But <abbr class=\"thlex-abbr\" title=\"Revised Standard Version (1952)\">RSV</abbr> and <abbr class=\"thlex-abbr\" title=\"New Revised Standard Version (1989)\">NRSV</abbr> suggest that this grating was near the top. It is probably better for translators to follow this interpretation.</p>\n<p>As can be seen from an overview of various translations, it is possible to translate <a href=\"https://ref.ly/Exod38:4\">EXO 38:4</a>; <a href=\"https://ref.ly/Exod38:5\">EXO 38:5</a> and the parallel passage in <a href=\"https://ref.ly/Exod27:4\">EXO 27:4</a>; <a href=\"https://ref.ly/Exod27:7\">EXO 27:7</a> without actually leaving the reader with a clear picture of how the grating, rim, and altar were related. While it is true that the functions of the rim and the grating are disputed, a clear description of one feasible option is to be preferred to a rendering that is meaningless to the reader. The following model is given in <em>A Handbook on Exodus</em> (page 635):</p>\n<p>4 Make a bronze grating, like a strainer, and attach a bronze ring at each of its four corners. 5 Then place the grating under the rim that goes around the altar, so that it extends halfway down inside the altar.</p>\n<p>Another possible model is:</p>\n<p>5 Build a rim around the altar near the top, and hang a bronze grating from it extending halfway down inside the altar. At each of the four corners of the grating attach a bronze ring.</p>\n<p>\n            <strong>Rings and poles</strong>: <a href=\"https://ref.ly/Exod27:4\">EXO 27:4</a> says that bronze rings were to be put on the “ends” or “edges” of the grating. Verse 7 describes the placing of the poles into “the rings, so that the poles shall be upon the two sides of the altar” (<abbr class=\"thlex-abbr\" title=\"Revised Standard Version (1952)\">RSV</abbr>). The Hebrew seems to indicate that there is only one set of rings, those attached to the grating, and that they were used to carry the entire altar. The placement of the rings will depend on the translator’s understanding of the grating as discussed above. If the “grating” is understood as a mesh going around the outside of the altar, then the rings are simply attached to the mesh. If, on the other hand, the “grating” is understood to be horizontal and sitting inside the altar, the rings projected through the corners of the altar so that the poles could be put through them.</p>\n<p>The poles were placed into the rings for carrying the altar, and they were probably removed after it had been set into place. Where a language distinguishes between installing an object permanently or temporarily, the latter option is the correct one here. This may mean using a different verb in <a href=\"https://ref.ly/Exod27:7\">EXO 27:7</a> from the one used in <a href=\"https://ref.ly/Exod25:14\">EXO 25:14</a> (see the discussion under <a class=\"thlex-xref\" data-bnType=\"lexiconLink\" data-collection=\"\" data-key=\"\" href=\"#\">4.1 Covenant Box, Ark of the Covenant&lt;REALIA:4.1&gt;</a>).</p>\n</div>\n</div>",
"associations": {
"passage": [
{
"start_ref": "02027004",
"start_ref_usfm": "EXO 27:4",
"end_ref": "02027004",
"end_ref_usfm": "EXO 27:4"
},
{
"start_ref": "02035016",
"start_ref_usfm": "EXO 35:16",
"end_ref": "02035016",
"end_ref_usfm": "EXO 35:16"
},
{
"start_ref": "02038005",
"start_ref_usfm": "EXO 38:5",
"end_ref": "02038005",
"end_ref_usfm": "EXO 38:5"
},
{
"start_ref": "02038030",
"start_ref_usfm": "EXO 38:30",
"end_ref": "02038030",
"end_ref_usfm": "EXO 38:30"
},
{
"start_ref": "02039039",
"start_ref_usfm": "EXO 39:39",
"end_ref": "02039039",
"end_ref_usfm": "EXO 39:39"
},
{
"start_ref": "02027007",
"start_ref_usfm": "EXO 27:7",
"end_ref": "02027007",
"end_ref_usfm": "EXO 27:7"
},
{
"start_ref": "02038007",
"start_ref_usfm": "EXO 38:7",
"end_ref": "02038007",
"end_ref_usfm": "EXO 38:7"
},
{
"start_ref": "02027006",
"start_ref_usfm": "EXO 27:6",
"end_ref": "02027006",
"end_ref_usfm": "EXO 27:6"
},
{
"start_ref": "02038006",
"start_ref_usfm": "EXO 38:6",
"end_ref": "02038006",
"end_ref_usfm": "EXO 38:6"
},
{
"start_ref": "30009009",
"start_ref_usfm": "AMO 9:9",
"end_ref": "30009009",
"end_ref_usfm": "AMO 9:9"
},
{
"start_ref": "02027005",
"start_ref_usfm": "EXO 27:5",
"end_ref": "02027005",
"end_ref_usfm": "EXO 27:5"
},
{
"start_ref": "02038004",
"start_ref_usfm": "EXO 38:4",
"end_ref": "02038004",
"end_ref_usfm": "EXO 38:4"
},
{
"start_ref": "02025014",
"start_ref_usfm": "EXO 25:14",
"end_ref": "02025014",
"end_ref_usfm": "EXO 25:14"
}
],
"resource": []
}
}
]