[
{
"content_id": "REALIA:3.14.3",
"reference_id": "REALIA:3.14.3",
"version": "1.0.4",
"title": "標題：塔、金字形廟塔（tower, ziggurat）",
"media_type": "Text",
"index_reference": "3.14.3",
"language": "zht",
"review_level": "None",
"content": "<style>\nh1.thlex-title { font-size: 1.3em; margin: 0 0 0.4em; }\n.thlex-key { color: #888; font-size: 0.85em; font-weight: normal; margin-right: 0.4em; }\nnav.thlex-index { margin: 0.5em 0 0.75em; }\nnav.thlex-index ul { margin: 0; padding-left: 1.2em; }\nnav.thlex-index li { margin: 0.15em 0; font-size: 0.95em; }\n.thlex-section { margin: 0.6em 0; }\nh2.thlex-heading { font-size: 1em; margin: 0.5em 0 0.2em; }\nh3.thlex-subheading { font-size: 0.95em; font-weight: normal; font-style: italic; margin: 0.2em 0; }\n.thlex-language-sets { margin: 0.3em 0 0.3em 1em; }\n.thlex-language-set { margin: 0.4em 0; padding-left: 0.75em; border-left: 3px solid #e0e0e0; }\n.thlex-language { font-size: 0.8em; color: #888; margin-right: 0.4em; }\n.thlex-lemma { font-weight: bold; font-family: serif; }\n.thlex-translit { color: #555; font-style: italic; font-size: 0.9em; margin-left: 0.3em; }\n.thlex-refs { font-size: 0.85em; color: #444; margin-top: 0.15em; }\n.thlex-paragraphs p { margin: 0.35em 0; font-size: 0.95em; line-height: 1.5; }\n.thlex-image { margin: 0.5em 0; display: block; }\n.thlex-image img { max-width: 100%; height: auto; display: block; }\nfigcaption.thlex-caption { font-size: 0.85em; color: #555; font-style: italic; margin-top: 0.2em; }\n.thlex-abbr { border-bottom: 1px dotted #888; cursor: help; }\n.thlex-xref { color: #1a5fb4; }\nspan[data-bnType=\"bibleReference\"] { color: #1a5fb4; }\ntable.thlex-table { border-collapse: collapse; font-size: 0.9em; margin: 0.5em 0; }\ntable.thlex-table td { padding: 0.2em 0.6em; vertical-align: top; border: 1px solid #ddd; }\ntable.thlex-table tr:first-child td { font-weight: bold; background: #f5f5f5; }\nul.thlex-index-list { margin: 0.4em 0; padding-left: 1.4em; font-size: 0.95em; line-height: 1.6; }\nul.thlex-index-list ul { margin: 0.1em 0; padding-left: 1.4em; }\n.thlex-index-key { font-weight: bold; font-style: italic; }\n</style><h1 class=\"thlex-title\" id=\"REALIA:3.14.3\"><span class=\"thlex-key\">3.14.3</span> 標題：塔、金字形廟塔（tower, ziggurat）</h1><div class=\"thlex-section\">\n<h2 class=\"thlex-heading\">經文出處</h2>\n<div class=\"thlex-language-sets\">\n<div class=\"thlex-language-set\">\n<span class=\"thlex-language\">Hebrew</span> <span class=\"thlex-lemma\">來： מִגְדָּל</span> <span class=\"thlex-translit\">(音譯： migdal)</span>\n<div class=\"thlex-refs\"><a href=\"https://ref.ly/Gen11:4\">GEN 11:4</a>, <a href=\"https://ref.ly/Gen11:5\">GEN 11:5</a></div>\n</div>\n</div>\n</div><div class=\"thlex-section\">\n<h2 class=\"thlex-heading\">描述和用途</h2>\n<div class=\"thlex-paragraphs\">\n<p>\n            <figure class=\"thlex-image\"><img class=\"thlex-img\" src=\"images/WEB-0425_ziggurat.jpg\" alt=\"巴比倫金字形神塔模型（埃特曼安吉模型（Model of Etemenanki），佩加蒙博物館（Pergamonmuseum），柏林）\"><figcaption class=\"thlex-caption\">巴比倫金字形神塔模型（埃特曼安吉模型（Model of Etemenanki），佩加蒙博物館（Pergamonmuseum），柏林） (O.Mustafin, CC0, via Wikimedia Commons)</figcaption></figure>金字型廟塔是一座非常高的塔，為宗教或儀式的目的而建造。廟塔的外面有階梯，頂部有一個神龕。</p>\n<hr/>\n</div>\n</div><div class=\"thlex-section\">\n<h2 class=\"thlex-heading\">翻譯</h2>\n<div class=\"thlex-paragraphs\">\n<p>在美索不達米亞有很雄偉壯觀的巨大構築物的廢墟，形狀是階梯式的塔或金字塔，稱為金字形廟塔。其中最重要的是吾珥廟塔和巴比倫廟塔，其年代分別可追溯到主前第三個千年末期和主前第二個千年初期。吾珥的金字形廟塔是方形的，寬43.3米（142英呎），長約62.5米（205英呎）。目前還無法精確計算它原來的高度，但看上去有7級或7層。<a href=\"https://ref.ly/Gen11:1\">GEN 11:1</a>; <a href=\"https://ref.ly/Gen11:2\">GEN 11:2</a>; <a href=\"https://ref.ly/Gen11:3\">GEN 11:3</a>; <a href=\"https://ref.ly/Gen11:4\">GEN 11:4</a>; <a href=\"https://ref.ly/Gen11:5\">GEN 11:5</a>; <a href=\"https://ref.ly/Gen11:6\">GEN 11:6</a>; <a href=\"https://ref.ly/Gen11:7\">GEN 11:7</a>; <a href=\"https://ref.ly/Gen11:8\">GEN 11:8</a>; <a href=\"https://ref.ly/Gen11:9\">GEN 11:9</a> 的記載似乎提到了巴比倫的金字形廟塔，中心部分由泥磚建成，厚約15米（50英呎）。金字形廟塔底下的平臺長457米（1,500英呎），寬415米（1,360英呎），但廟塔本身的邊長只有91.5米（300英呎）。和吾珥的金字形廟塔一樣，巴比倫金字形廟塔也有三段階梯，兩側的階梯高30.5米（100英呎），中間的階梯高40米（132英呎）。根據附近的埃薩吉拉（Esagil）神廟廢墟中發現的石碑記載，塔的高度約有91.5米（300英呎）。希臘歷史學家希羅多德（《歷史》第1卷，第181［185］頁）記述該廟塔為正方形，有8層或「塔」，一層疊一層。巴比倫廟塔和吾珥的金字形廟塔一樣，在差不多中心的位置也有一座神龕，其通道有一部分是臺階，有一部分是斜坡。</p>\n<p>在大多數譯本中，將<a href=\"https://ref.ly/Gen11:4\">GEN 11:4</a>; <a href=\"https://ref.ly/Gen11:5\">GEN 11:5</a> 中的希伯來文<em>migdal</em> 翻譯成「塔」就足夠了。如果目標語言中沒有合適的詞，翻譯者可以譯為「有很多層的高房子」，甚至是「非常高的梯子」。</p>\n</div>\n</div>",
"associations": {
"passage": [
{
"start_ref": "01011004",
"start_ref_usfm": "GEN 11:4",
"end_ref": "01011004",
"end_ref_usfm": "GEN 11:4"
},
{
"start_ref": "01011005",
"start_ref_usfm": "GEN 11:5",
"end_ref": "01011005",
"end_ref_usfm": "GEN 11:5"
},
{
"start_ref": "01011001",
"start_ref_usfm": "GEN 11:1",
"end_ref": "01011001",
"end_ref_usfm": "GEN 11:1"
},
{
"start_ref": "01011002",
"start_ref_usfm": "GEN 11:2",
"end_ref": "01011002",
"end_ref_usfm": "GEN 11:2"
},
{
"start_ref": "01011003",
"start_ref_usfm": "GEN 11:3",
"end_ref": "01011003",
"end_ref_usfm": "GEN 11:3"
},
{
"start_ref": "01011006",
"start_ref_usfm": "GEN 11:6",
"end_ref": "01011006",
"end_ref_usfm": "GEN 11:6"
},
{
"start_ref": "01011007",
"start_ref_usfm": "GEN 11:7",
"end_ref": "01011007",
"end_ref_usfm": "GEN 11:7"
},
{
"start_ref": "01011008",
"start_ref_usfm": "GEN 11:8",
"end_ref": "01011008",
"end_ref_usfm": "GEN 11:8"
},
{
"start_ref": "01011009",
"start_ref_usfm": "GEN 11:9",
"end_ref": "01011009",
"end_ref_usfm": "GEN 11:9"
}
],
"resource": [],
"acai": []
}
}
]